fartlib/__init__.py
fartlib-2.0.1.dist-info/licenses/LICENSE
fartlib-2.0.1.dist-info/METADATA
fartlib-2.0.1.dist-info/WHEEL
fartlib-2.0.1.dist-info/top_level.txt
fartlib-2.0.1.dist-info/RECORD
