Metadata-Version: 2.4
Name: fartlib
Version: 2.0.1
Summary: the official fartlib package
Home-page: https://github.com/adondonis/fartlib
Author: Adonis
Classifier: Programming Language :: Python :: 3
Classifier: License :: OSI Approved :: MIT License
Classifier: Operating System :: OS Independent
Requires-Python: >=3.7
License-File: LICENSE
Dynamic: author
Dynamic: classifier
Dynamic: description
Dynamic: description-content-type
Dynamic: home-page
Dynamic: license-file
Dynamic: requires-python
Dynamic: summary
